{
    "originSize": {
        "height": 351,
        "width": 250
    },
    "sections": [
        [
            {
                "blocks": [
                    [
                        {
                            "Pos": {
                                "X": 0,
                                "Y": 68
                            },
                            "Color": {
                                "R": 234,
                                "G": 186,
                                "B": 118
                            }
                        },
                        {
                            "Pos": {
                                "X": 12,
                                "Y": 68
                            },
                            "Color": {
                                "R": 190,
                                "G": 194,
                                "B": 174
                            }
                        },
                        {
                            "Pos": {
                                "X": 24,
                                "Y": 68
                            },
                            "Color": {
                                "R": 236,
                                "G": 221,
                                "B": 202
                            }
                        },
                        {
                            "Pos": {
                                "X": 36,
                                "Y": 68
                            },
                            "Color": {
                                "R": 236,
                                "G": 221,
                                "B": 202
                            }
                        },
                        {
                            "Pos": {
                                "X": 48,
                                "Y": 68
                            },
                            "Color": {
                                "R": 236,
                                "G": 221,
                                "B": 202
                            }
                        }
                    ]
                ],
                "isVisible": false,
                "used_colors": [
                    [
                        {
                            "R": 202,
                            "G": 62,
                            "B": 59
                        },
                        {
                            "R": 196,
                            "G": 197,
                            "B": 180
                        },
                        {
                            "R": 236,
                            "G": 223,
                            "B": 206
                        }
                    ]
                ]
            },
            {
                "blocks": [
                    [
                        {
                            "Pos": {
                                "X": 0,
                                "Y": 68
                            },
                            "Color": {
                                "R": 234,
                                "G": 186,
                                "B": 118
                            }
                        },
                        {
                            "Pos": {
                                "X": 12,
                                "Y": 68
                            },
                            "Color": {
                                "R": 190,
                                "G": 194,
                                "B": 174
                            }
                        },
                        {
                            "Pos": {
                                "X": 24,
                                "Y": 68
                            },
                            "Color": {
                                "R": 236,
                                "G": 221,
                                "B": 202
                            }
                        },
                        {
                            "Pos": {
                                "X": 36,
                                "Y": 68
                            },
                            "Color": {
                                "R": 236,
                                "G": 221,
                                "B": 202
                            }
                        },
                        {
                            "Pos": {
                                "X": 48,
                                "Y": 68
                            },
                            "Color": {
                                "R": 236,
                                "G": 221,
                                "B": 202
                            }
                        }
                    ]
                ],
                "isVisible": false,
                "used_colors": [
                    [
                        {
                            "R": 200,
                            "G": 63,
                            "B": 55
                        },
                        {
                            "R": 237,
                            "G": 224,
                            "B": 204
                        },
                        {
                            "R": 149,
                            "G": 58,
                            "B": 51
                        },
                        {
                            "R": 161,
                            "G": 104,
                            "B": 96
                        }
                    ]
                ]
            },
            {
                "blocks": [
                    [
                        {
                            "Pos": {
                                "X": 0,
                                "Y": 68
                            },
                            "Color": {
                                "R": 234,
                                "G": 186,
                                "B": 118
                            }
                        },
                        {
                            "Pos": {
                                "X": 12,
                                "Y": 68
                            },
                            "Color": {
                                "R": 190,
                                "G": 194,
                                "B": 174
                            }
                        },
                        {
                            "Pos": {
                                "X": 24,
                                "Y": 68
                            },
                            "Color": {
                                "R": 236,
                                "G": 221,
                                "B": 202
                            }
                        },
                        {
                            "Pos": {
                                "X": 36,
                                "Y": 68
                            },
                            "Color": {
                                "R": 236,
                                "G": 221,
                                "B": 202
                            }
                        },
                        {
                            "Pos": {
                                "X": 48,
                                "Y": 68
                            },
                            "Color": {
                                "R": 236,
                                "G": 221,
                                "B": 202
                            }
                        }
                    ]
                ],
                "isVisible": false,
                "used_colors": [
                    [
                        {
                            "R": 179,
                            "G": 155,
                            "B": 93
                        },
                        {
                            "R": 236,
                            "G": 223,
                            "B": 204
                        },
                        {
                            "R": 95,
                            "G": 109,
                            "B": 72
                        },
                        {
                            "R": 200,
                            "G": 63,
                            "B": 55
                        }
                    ]
                ]
            },
            {
                "blocks": [
                    [
                        {
                            "Pos": {
                                "X": 0,
                                "Y": 68
                            },
                            "Color": {
                                "R": 234,
                                "G": 186,
                                "B": 118
                            }
                        },
                        {
                            "Pos": {
                                "X": 12,
                                "Y": 68
                            },
                            "Color": {
                                "R": 190,
                                "G": 194,
                                "B": 174
                            }
                        },
                        {
                            "Pos": {
                                "X": 24,
                                "Y": 68
                            },
                            "Color": {
                                "R": 236,
                                "G": 221,
                                "B": 202
                            }
                        },
                        {
                            "Pos": {
                                "X": 36,
                                "Y": 68
                            },
                            "Color": {
                                "R": 236,
                                "G": 221,
                                "B": 202
                            }
                        },
                        {
                            "Pos": {
                                "X": 48,
                                "Y": 68
                            },
                            "Color": {
                                "R": 236,
                                "G": 221,
                                "B": 202
                            }
                        }
                    ]
                ],
                "isVisible": false,
                "used_colors": [
                    [
                        {
                            "R": 236,
                            "G": 223,
                            "B": 204
                        },
                        {
                            "R": 74,
                            "G": 123,
                            "B": 98
                        },
                        {
                            "R": 164,
                            "G": 102,
                            "B": 81
                        },
                        {
                            "R": 178,
                            "G": 182,
                            "B": 164
                        }
                    ]
                ]
            }
        ],
        [
            {
                "blocks": [
                    [
                        {
                            "Pos": {
                                "X": 0,
                                "Y": 68
                            },
                            "Color": {
                                "R": 234,
                                "G": 186,
                                "B": 118
                            }
                        },
                        {
                            "Pos": {
                                "X": 12,
                                "Y": 68
                            },
                            "Color": {
                                "R": 190,
                                "G": 194,
                                "B": 174
                            }
                        },
                        {
                            "Pos": {
                                "X": 24,
                                "Y": 68
                            },
                            "Color": {
                                "R": 236,
                                "G": 221,
                                "B": 202
                            }
                        },
                        {
                            "Pos": {
                                "X": 36,
                                "Y": 68
                            },
                            "Color": {
                                "R": 236,
                                "G": 221,
                                "B": 202
                            }
                        },
                        {
                            "Pos": {
                                "X": 48,
                                "Y": 68
                            },
                            "Color": {
                                "R": 236,
                                "G": 221,
                                "B": 202
                            }
                        }
                    ]
                ],
                "isVisible": false,
                "used_colors": [
                    [
                        {
                            "R": 189,
                            "G": 102,
                            "B": 89
                        },
                        {
                            "R": 230,
                            "G": 220,
                            "B": 201
                        },
                        {
                            "R": 192,
                            "G": 198,
                            "B": 175
                        }
                    ]
                ]
            },
            {
                "blocks": [
                    [
                        {
                            "Pos": {
                                "X": 0,
                                "Y": 68
                            },
                            "Color": {
                                "R": 234,
                                "G": 186,
                                "B": 118
                            }
                        },
                        {
                            "Pos": {
                                "X": 12,
                                "Y": 68
                            },
                            "Color": {
                                "R": 190,
                                "G": 194,
                                "B": 174
                            }
                        },
                        {
                            "Pos": {
                                "X": 24,
                                "Y": 68
                            },
                            "Color": {
                                "R": 236,
                                "G": 221,
                                "B": 202
                            }
                        },
                        {
                            "Pos": {
                                "X": 36,
                                "Y": 68
                            },
                            "Color": {
                                "R": 236,
                                "G": 221,
                                "B": 202
                            }
                        },
                        {
                            "Pos": {
                                "X": 48,
                                "Y": 68
                            },
                            "Color": {
                                "R": 236,
                                "G": 221,
                                "B": 202
                            }
                        }
                    ]
                ],
                "isVisible": false,
                "used_colors": [
                    [
                        {
                            "R": 139,
                            "G": 150,
                            "B": 160
                        },
                        {
                            "R": 228,
                            "G": 179,
                            "B": 126
                        },
                        {
                            "R": 203,
                            "G": 65,
                            "B": 55
                        },
                        {
                            "R": 236,
                            "G": 223,
                            "B": 204
                        }
                    ]
                ]
            },
            {
                "blocks": [
                    [
                        {
                            "Pos": {
                                "X": 0,
                                "Y": 68
                            },
                            "Color": {
                                "R": 234,
                                "G": 186,
                                "B": 118
                            }
                        },
                        {
                            "Pos": {
                                "X": 12,
                                "Y": 68
                            },
                            "Color": {
                                "R": 190,
                                "G": 194,
                                "B": 174
                            }
                        },
                        {
                            "Pos": {
                                "X": 24,
                                "Y": 68
                            },
                            "Color": {
                                "R": 236,
                                "G": 221,
                                "B": 202
                            }
                        },
                        {
                            "Pos": {
                                "X": 36,
                                "Y": 68
                            },
                            "Color": {
                                "R": 236,
                                "G": 221,
                                "B": 202
                            }
                        },
                        {
                            "Pos": {
                                "X": 48,
                                "Y": 68
                            },
                            "Color": {
                                "R": 236,
                                "G": 221,
                                "B": 202
                            }
                        }
                    ]
                ],
                "isVisible": false,
                "used_colors": [
                    [
                        {
                            "R": 124,
                            "G": 137,
                            "B": 149
                        },
                        {
                            "R": 221,
                            "G": 138,
                            "B": 85
                        },
                        {
                            "R": 236,
                            "G": 223,
                            "B": 204
                        }
                    ]
                ]
            },
            {
                "blocks": [
                    [
                        {
                            "Pos": {
                                "X": 0,
                                "Y": 68
                            },
                            "Color": {
                                "R": 234,
                                "G": 186,
                                "B": 118
                            }
                        },
                        {
                            "Pos": {
                                "X": 12,
                                "Y": 68
                            },
                            "Color": {
                                "R": 190,
                                "G": 194,
                                "B": 174
                            }
                        },
                        {
                            "Pos": {
                                "X": 24,
                                "Y": 68
                            },
                            "Color": {
                                "R": 236,
                                "G": 221,
                                "B": 202
                            }
                        },
                        {
                            "Pos": {
                                "X": 36,
                                "Y": 68
                            },
                            "Color": {
                                "R": 236,
                                "G": 221,
                                "B": 202
                            }
                        },
                        {
                            "Pos": {
                                "X": 48,
                                "Y": 68
                            },
                            "Color": {
                                "R": 236,
                                "G": 221,
                                "B": 202
                            }
                        }
                    ]
                ],
                "isVisible": false,
                "used_colors": [
                    [
                        {
                            "R": 158,
                            "G": 168,
                            "B": 172
                        },
                        {
                            "R": 237,
                            "G": 222,
                            "B": 203
                        },
                        {
                            "R": 120,
                            "G": 141,
                            "B": 144
                        },
                        {
                            "R": 193,
                            "G": 67,
                            "B": 56
                        }
                    ]
                ]
            }
        ],
        [
            {
                "blocks": [
                    [
                        {
                            "Pos": {
                                "X": 0,
                                "Y": 68
                            },
                            "Color": {
                                "R": 234,
                                "G": 186,
                                "B": 118
                            }
                        },
                        {
                            "Pos": {
                                "X": 12,
                                "Y": 68
                            },
                            "Color": {
                                "R": 190,
                                "G": 194,
                                "B": 174
                            }
                        },
                        {
                            "Pos": {
                                "X": 24,
                                "Y": 68
                            },
                            "Color": {
                                "R": 236,
                                "G": 221,
                                "B": 202
                            }
                        },
                        {
                            "Pos": {
                                "X": 36,
                                "Y": 68
                            },
                            "Color": {
                                "R": 236,
                                "G": 221,
                                "B": 202
                            }
                        },
                        {
                            "Pos": {
                                "X": 48,
                                "Y": 68
                            },
                            "Color": {
                                "R": 236,
                                "G": 221,
                                "B": 202
                            }
                        }
                    ]
                ],
                "isVisible": false,
                "used_colors": [
                    [
                        {
                            "R": 220,
                            "G": 127,
                            "B": 107
                        },
                        {
                            "R": 232,
                            "G": 181,
                            "B": 154
                        },
                        {
                            "R": 171,
                            "G": 181,
                            "B": 156
                        },
                        {
                            "R": 235,
                            "G": 222,
                            "B": 203
                        }
                    ]
                ]
            },
            {
                "blocks": [
                    [
                        {
                            "Pos": {
                                "X": 0,
                                "Y": 68
                            },
                            "Color": {
                                "R": 234,
                                "G": 186,
                                "B": 118
                            }
                        },
                        {
                            "Pos": {
                                "X": 12,
                                "Y": 68
                            },
                            "Color": {
                                "R": 190,
                                "G": 194,
                                "B": 174
                            }
                        },
                        {
                            "Pos": {
                                "X": 24,
                                "Y": 68
                            },
                            "Color": {
                                "R": 236,
                                "G": 221,
                                "B": 202
                            }
                        },
                        {
                            "Pos": {
                                "X": 36,
                                "Y": 68
                            },
                            "Color": {
                                "R": 236,
                                "G": 221,
                                "B": 202
                            }
                        },
                        {
                            "Pos": {
                                "X": 48,
                                "Y": 68
                            },
                            "Color": {
                                "R": 236,
                                "G": 221,
                                "B": 202
                            }
                        }
                    ]
                ],
                "isVisible": false,
                "used_colors": [
                    [
                        {
                            "R": 223,
                            "G": 163,
                            "B": 107
                        },
                        {
                            "R": 236,
                            "G": 223,
                            "B": 204
                        },
                        {
                            "R": 178,
                            "G": 83,
                            "B": 58
                        },
                        {
                            "R": 137,
                            "G": 147,
                            "B": 161
                        }
                    ]
                ]
            },
            {
                "blocks": [
                    [
                        {
                            "Pos": {
                                "X": 0,
                                "Y": 68
                            },
                            "Color": {
                                "R": 234,
                                "G": 186,
                                "B": 118
                            }
                        },
                        {
                            "Pos": {
                                "X": 12,
                                "Y": 68
                            },
                            "Color": {
                                "R": 190,
                                "G": 194,
                                "B": 174
                            }
                        },
                        {
                            "Pos": {
                                "X": 24,
                                "Y": 68
                            },
                            "Color": {
                                "R": 236,
                                "G": 221,
                                "B": 202
                            }
                        },
                        {
                            "Pos": {
                                "X": 36,
                                "Y": 68
                            },
                            "Color": {
                                "R": 236,
                                "G": 221,
                                "B": 202
                            }
                        },
                        {
                            "Pos": {
                                "X": 48,
                                "Y": 68
                            },
                            "Color": {
                                "R": 236,
                                "G": 221,
                                "B": 202
                            }
                        }
                    ]
                ],
                "isVisible": false,
                "used_colors": [
                    [
                        {
                            "R": 230,
                            "G": 176,
                            "B": 110
                        },
                        {
                            "R": 246,
                            "G": 207,
                            "B": 146
                        }
                    ]
                ]
            },
            {
                "blocks": [
                    [
                        {
                            "Pos": {
                                "X": 0,
                                "Y": 68
                            },
                            "Color": {
                                "R": 234,
                                "G": 186,
                                "B": 118
                            }
                        },
                        {
                            "Pos": {
                                "X": 12,
                                "Y": 68
                            },
                            "Color": {
                                "R": 190,
                                "G": 194,
                                "B": 174
                            }
                        },
                        {
                            "Pos": {
                                "X": 24,
                                "Y": 68
                            },
                            "Color": {
                                "R": 236,
                                "G": 221,
                                "B": 202
                            }
                        },
                        {
                            "Pos": {
                                "X": 36,
                                "Y": 68
                            },
                            "Color": {
                                "R": 236,
                                "G": 221,
                                "B": 202
                            }
                        },
                        {
                            "Pos": {
                                "X": 48,
                                "Y": 68
                            },
                            "Color": {
                                "R": 236,
                                "G": 221,
                                "B": 202
                            }
                        }
                    ]
                ],
                "isVisible": false,
                "used_colors": [
                    [
                        {
                            "R": 231,
                            "G": 193,
                            "B": 134
                        },
                        {
                            "R": 237,
                            "G": 222,
                            "B": 203
                        },
                        {
                            "R": 192,
                            "G": 194,
                            "B": 175
                        }
                    ]
                ]
            }
        ],
        [
            {
                "blocks": [
                    [
                        {
                            "Pos": {
                                "X": 0,
                                "Y": 68
                            },
                            "Color": {
                                "R": 234,
                                "G": 186,
                                "B": 118
                            }
                        },
                        {
                            "Pos": {
                                "X": 12,
                                "Y": 68
                            },
                            "Color": {
                                "R": 190,
                                "G": 194,
                                "B": 174
                            }
                        },
                        {
                            "Pos": {
                                "X": 24,
                                "Y": 68
                            },
                            "Color": {
                                "R": 236,
                                "G": 221,
                                "B": 202
                            }
                        },
                        {
                            "Pos": {
                                "X": 36,
                                "Y": 68
                            },
                            "Color": {
                                "R": 236,
                                "G": 221,
                                "B": 202
                            }
                        },
                        {
                            "Pos": {
                                "X": 48,
                                "Y": 68
                            },
                            "Color": {
                                "R": 236,
                                "G": 221,
                                "B": 202
                            }
                        }
                    ]
                ],
                "isVisible": false,
                "used_colors": [
                    [
                        {
                            "R": 236,
                            "G": 221,
                            "B": 202
                        },
                        {
                            "R": 188,
                            "G": 165,
                            "B": 81
                        },
                        {
                            "R": 235,
                            "G": 199,
                            "B": 111
                        },
                        {
                            "R": 184,
                            "G": 190,
                            "B": 169
                        }
                    ]
                ]
            },
            {
                "blocks": [
                    [
                        {
                            "Pos": {
                                "X": 0,
                                "Y": 68
                            },
                            "Color": {
                                "R": 234,
                                "G": 186,
                                "B": 118
                            }
                        },
                        {
                            "Pos": {
                                "X": 12,
                                "Y": 68
                            },
                            "Color": {
                                "R": 190,
                                "G": 194,
                                "B": 174
                            }
                        },
                        {
                            "Pos": {
                                "X": 24,
                                "Y": 68
                            },
                            "Color": {
                                "R": 236,
                                "G": 221,
                                "B": 202
                            }
                        },
                        {
                            "Pos": {
                                "X": 36,
                                "Y": 68
                            },
                            "Color": {
                                "R": 236,
                                "G": 221,
                                "B": 202
                            }
                        },
                        {
                            "Pos": {
                                "X": 48,
                                "Y": 68
                            },
                            "Color": {
                                "R": 236,
                                "G": 221,
                                "B": 202
                            }
                        }
                    ]
                ],
                "isVisible": false,
                "used_colors": [
                    [
                        {
                            "R": 236,
                            "G": 195,
                            "B": 105
                        },
                        {
                            "R": 235,
                            "G": 222,
                            "B": 203
                        },
                        {
                            "R": 194,
                            "G": 167,
                            "B": 91
                        },
                        {
                            "R": 208,
                            "G": 80,
                            "B": 57
                        }
                    ]
                ]
            },
            {
                "blocks": [
                    [
                        {
                            "Pos": {
                                "X": 0,
                                "Y": 68
                            },
                            "Color": {
                                "R": 234,
                                "G": 186,
                                "B": 118
                            }
                        },
                        {
                            "Pos": {
                                "X": 12,
                                "Y": 68
                            },
                            "Color": {
                                "R": 190,
                                "G": 194,
                                "B": 174
                            }
                        },
                        {
                            "Pos": {
                                "X": 24,
                                "Y": 68
                            },
                            "Color": {
                                "R": 236,
                                "G": 221,
                                "B": 202
                            }
                        },
                        {
                            "Pos": {
                                "X": 36,
                                "Y": 68
                            },
                            "Color": {
                                "R": 236,
                                "G": 221,
                                "B": 202
                            }
                        },
                        {
                            "Pos": {
                                "X": 48,
                                "Y": 68
                            },
                            "Color": {
                                "R": 236,
                                "G": 221,
                                "B": 202
                            }
                        }
                    ]
                ],
                "isVisible": false,
                "used_colors": [
                    [
                        {
                            "R": 234,
                            "G": 183,
                            "B": 118
                        },
                        {
                            "R": 233,
                            "G": 227,
                            "B": 204
                        }
                    ]
                ]
            },
            {
                "blocks": [
                    [
                        {
                            "Pos": {
                                "X": 0,
                                "Y": 68
                            },
                            "Color": {
                                "R": 234,
                                "G": 186,
                                "B": 118
                            }
                        },
                        {
                            "Pos": {
                                "X": 12,
                                "Y": 68
                            },
                            "Color": {
                                "R": 190,
                                "G": 194,
                                "B": 174
                            }
                        },
                        {
                            "Pos": {
                                "X": 24,
                                "Y": 68
                            },
                            "Color": {
                                "R": 236,
                                "G": 221,
                                "B": 202
                            }
                        },
                        {
                            "Pos": {
                                "X": 36,
                                "Y": 68
                            },
                            "Color": {
                                "R": 236,
                                "G": 221,
                                "B": 202
                            }
                        },
                        {
                            "Pos": {
                                "X": 48,
                                "Y": 68
                            },
                            "Color": {
                                "R": 236,
                                "G": 221,
                                "B": 202
                            }
                        }
                    ]
                ],
                "isVisible": false,
                "used_colors": [
                    [
                        {
                            "R": 234,
                            "G": 186,
                            "B": 118
                        },
                        {
                            "R": 236,
                            "G": 221,
                            "B": 202
                        },
                        {
                            "R": 190,
                            "G": 194,
                            "B": 174
                        }
                    ]
                ]
            }
        ]
    ]
}