{
    "originSize": {
        "height": 347,
        "width": 250
    },
    "sections": [
        [
            {
                "blocks": [
                    [
                        {
                            "Pos": {
                                "X": 0,
                                "Y": 68
                            },
                            "Color": {
                                "R": 157,
                                "G": 123,
                                "B": 88
                            }
                        },
                        {
                            "Pos": {
                                "X": 12,
                                "Y": 68
                            },
                            "Color": {
                                "R": 157,
                                "G": 123,
                                "B": 88
                            }
                        },
                        {
                            "Pos": {
                                "X": 24,
                                "Y": 68
                            },
                            "Color": {
                                "R": 157,
                                "G": 123,
                                "B": 88
                            }
                        },
                        {
                            "Pos": {
                                "X": 36,
                                "Y": 68
                            },
                            "Color": {
                                "R": 157,
                                "G": 123,
                                "B": 88
                            }
                        },
                        {
                            "Pos": {
                                "X": 48,
                                "Y": 68
                            },
                            "Color": {
                                "R": 157,
                                "G": 123,
                                "B": 88
                            }
                        }
                    ]
                ],
                "isVisible": false,
                "used_colors": [
                    [
                        {
                            "R": 150,
                            "G": 169,
                            "B": 183
                        },
                        {
                            "R": 185,
                            "G": 148,
                            "B": 107
                        }
                    ]
                ]
            },
            {
                "blocks": [
                    [
                        {
                            "Pos": {
                                "X": 0,
                                "Y": 68
                            },
                            "Color": {
                                "R": 157,
                                "G": 123,
                                "B": 88
                            }
                        },
                        {
                            "Pos": {
                                "X": 12,
                                "Y": 68
                            },
                            "Color": {
                                "R": 157,
                                "G": 123,
                                "B": 88
                            }
                        },
                        {
                            "Pos": {
                                "X": 24,
                                "Y": 68
                            },
                            "Color": {
                                "R": 157,
                                "G": 123,
                                "B": 88
                            }
                        },
                        {
                            "Pos": {
                                "X": 36,
                                "Y": 68
                            },
                            "Color": {
                                "R": 157,
                                "G": 123,
                                "B": 88
                            }
                        },
                        {
                            "Pos": {
                                "X": 48,
                                "Y": 68
                            },
                            "Color": {
                                "R": 157,
                                "G": 123,
                                "B": 88
                            }
                        }
                    ]
                ],
                "isVisible": false,
                "used_colors": [
                    [
                        {
                            "R": 202,
                            "G": 169,
                            "B": 131
                        },
                        {
                            "R": 160,
                            "G": 175,
                            "B": 180
                        },
                        {
                            "R": 168,
                            "G": 138,
                            "B": 110
                        }
                    ]
                ]
            },
            {
                "blocks": [
                    [
                        {
                            "Pos": {
                                "X": 0,
                                "Y": 68
                            },
                            "Color": {
                                "R": 157,
                                "G": 123,
                                "B": 88
                            }
                        },
                        {
                            "Pos": {
                                "X": 12,
                                "Y": 68
                            },
                            "Color": {
                                "R": 157,
                                "G": 123,
                                "B": 88
                            }
                        },
                        {
                            "Pos": {
                                "X": 24,
                                "Y": 68
                            },
                            "Color": {
                                "R": 157,
                                "G": 123,
                                "B": 88
                            }
                        },
                        {
                            "Pos": {
                                "X": 36,
                                "Y": 68
                            },
                            "Color": {
                                "R": 157,
                                "G": 123,
                                "B": 88
                            }
                        },
                        {
                            "Pos": {
                                "X": 48,
                                "Y": 68
                            },
                            "Color": {
                                "R": 157,
                                "G": 123,
                                "B": 88
                            }
                        }
                    ]
                ],
                "isVisible": false,
                "used_colors": [
                    [
                        {
                            "R": 168,
                            "G": 142,
                            "B": 105
                        },
                        {
                            "R": 169,
                            "G": 180,
                            "B": 176
                        },
                        {
                            "R": 206,
                            "G": 166,
                            "B": 130
                        }
                    ]
                ]
            },
            {
                "blocks": [
                    [
                        {
                            "Pos": {
                                "X": 0,
                                "Y": 68
                            },
                            "Color": {
                                "R": 157,
                                "G": 123,
                                "B": 88
                            }
                        },
                        {
                            "Pos": {
                                "X": 12,
                                "Y": 68
                            },
                            "Color": {
                                "R": 157,
                                "G": 123,
                                "B": 88
                            }
                        },
                        {
                            "Pos": {
                                "X": 24,
                                "Y": 68
                            },
                            "Color": {
                                "R": 157,
                                "G": 123,
                                "B": 88
                            }
                        },
                        {
                            "Pos": {
                                "X": 36,
                                "Y": 68
                            },
                            "Color": {
                                "R": 157,
                                "G": 123,
                                "B": 88
                            }
                        },
                        {
                            "Pos": {
                                "X": 48,
                                "Y": 68
                            },
                            "Color": {
                                "R": 157,
                                "G": 123,
                                "B": 88
                            }
                        }
                    ]
                ],
                "isVisible": false,
                "used_colors": [
                    [
                        {
                            "R": 164,
                            "G": 173,
                            "B": 169
                        },
                        {
                            "R": 183,
                            "G": 145,
                            "B": 107
                        }
                    ]
                ]
            }
        ],
        [
            {
                "blocks": [
                    [
                        {
                            "Pos": {
                                "X": 0,
                                "Y": 68
                            },
                            "Color": {
                                "R": 157,
                                "G": 123,
                                "B": 88
                            }
                        },
                        {
                            "Pos": {
                                "X": 12,
                                "Y": 68
                            },
                            "Color": {
                                "R": 157,
                                "G": 123,
                                "B": 88
                            }
                        },
                        {
                            "Pos": {
                                "X": 24,
                                "Y": 68
                            },
                            "Color": {
                                "R": 157,
                                "G": 123,
                                "B": 88
                            }
                        },
                        {
                            "Pos": {
                                "X": 36,
                                "Y": 68
                            },
                            "Color": {
                                "R": 157,
                                "G": 123,
                                "B": 88
                            }
                        },
                        {
                            "Pos": {
                                "X": 48,
                                "Y": 68
                            },
                            "Color": {
                                "R": 157,
                                "G": 123,
                                "B": 88
                            }
                        }
                    ]
                ],
                "isVisible": false,
                "used_colors": [
                    [
                        {
                            "R": 206,
                            "G": 163,
                            "B": 121
                        },
                        {
                            "R": 235,
                            "G": 201,
                            "B": 163
                        }
                    ]
                ]
            },
            {
                "blocks": [
                    [
                        {
                            "Pos": {
                                "X": 0,
                                "Y": 68
                            },
                            "Color": {
                                "R": 157,
                                "G": 123,
                                "B": 88
                            }
                        },
                        {
                            "Pos": {
                                "X": 12,
                                "Y": 68
                            },
                            "Color": {
                                "R": 157,
                                "G": 123,
                                "B": 88
                            }
                        },
                        {
                            "Pos": {
                                "X": 24,
                                "Y": 68
                            },
                            "Color": {
                                "R": 157,
                                "G": 123,
                                "B": 88
                            }
                        },
                        {
                            "Pos": {
                                "X": 36,
                                "Y": 68
                            },
                            "Color": {
                                "R": 157,
                                "G": 123,
                                "B": 88
                            }
                        },
                        {
                            "Pos": {
                                "X": 48,
                                "Y": 68
                            },
                            "Color": {
                                "R": 157,
                                "G": 123,
                                "B": 88
                            }
                        }
                    ]
                ],
                "isVisible": false,
                "used_colors": [
                    [
                        {
                            "R": 237,
                            "G": 202,
                            "B": 162
                        },
                        {
                            "R": 184,
                            "G": 140,
                            "B": 98
                        },
                        {
                            "R": 157,
                            "G": 113,
                            "B": 74
                        }
                    ]
                ]
            },
            {
                "blocks": [
                    [
                        {
                            "Pos": {
                                "X": 0,
                                "Y": 68
                            },
                            "Color": {
                                "R": 157,
                                "G": 123,
                                "B": 88
                            }
                        },
                        {
                            "Pos": {
                                "X": 12,
                                "Y": 68
                            },
                            "Color": {
                                "R": 157,
                                "G": 123,
                                "B": 88
                            }
                        },
                        {
                            "Pos": {
                                "X": 24,
                                "Y": 68
                            },
                            "Color": {
                                "R": 157,
                                "G": 123,
                                "B": 88
                            }
                        },
                        {
                            "Pos": {
                                "X": 36,
                                "Y": 68
                            },
                            "Color": {
                                "R": 157,
                                "G": 123,
                                "B": 88
                            }
                        },
                        {
                            "Pos": {
                                "X": 48,
                                "Y": 68
                            },
                            "Color": {
                                "R": 157,
                                "G": 123,
                                "B": 88
                            }
                        }
                    ]
                ],
                "isVisible": false,
                "used_colors": [
                    [
                        {
                            "R": 231,
                            "G": 191,
                            "B": 149
                        },
                        {
                            "R": 144,
                            "G": 103,
                            "B": 65
                        }
                    ]
                ]
            },
            {
                "blocks": [
                    [
                        {
                            "Pos": {
                                "X": 0,
                                "Y": 68
                            },
                            "Color": {
                                "R": 157,
                                "G": 123,
                                "B": 88
                            }
                        },
                        {
                            "Pos": {
                                "X": 12,
                                "Y": 68
                            },
                            "Color": {
                                "R": 157,
                                "G": 123,
                                "B": 88
                            }
                        },
                        {
                            "Pos": {
                                "X": 24,
                                "Y": 68
                            },
                            "Color": {
                                "R": 157,
                                "G": 123,
                                "B": 88
                            }
                        },
                        {
                            "Pos": {
                                "X": 36,
                                "Y": 68
                            },
                            "Color": {
                                "R": 157,
                                "G": 123,
                                "B": 88
                            }
                        },
                        {
                            "Pos": {
                                "X": 48,
                                "Y": 68
                            },
                            "Color": {
                                "R": 157,
                                "G": 123,
                                "B": 88
                            }
                        }
                    ]
                ],
                "isVisible": false,
                "used_colors": [
                    [
                        {
                            "R": 167,
                            "G": 130,
                            "B": 96
                        },
                        {
                            "R": 225,
                            "G": 189,
                            "B": 161
                        }
                    ]
                ]
            }
        ],
        [
            {
                "blocks": [
                    [
                        {
                            "Pos": {
                                "X": 0,
                                "Y": 68
                            },
                            "Color": {
                                "R": 157,
                                "G": 123,
                                "B": 88
                            }
                        },
                        {
                            "Pos": {
                                "X": 12,
                                "Y": 68
                            },
                            "Color": {
                                "R": 157,
                                "G": 123,
                                "B": 88
                            }
                        },
                        {
                            "Pos": {
                                "X": 24,
                                "Y": 68
                            },
                            "Color": {
                                "R": 157,
                                "G": 123,
                                "B": 88
                            }
                        },
                        {
                            "Pos": {
                                "X": 36,
                                "Y": 68
                            },
                            "Color": {
                                "R": 157,
                                "G": 123,
                                "B": 88
                            }
                        },
                        {
                            "Pos": {
                                "X": 48,
                                "Y": 68
                            },
                            "Color": {
                                "R": 157,
                                "G": 123,
                                "B": 88
                            }
                        }
                    ]
                ],
                "isVisible": false,
                "used_colors": [
                    [
                        {
                            "R": 135,
                            "G": 124,
                            "B": 79
                        },
                        {
                            "R": 248,
                            "G": 208,
                            "B": 173
                        },
                        {
                            "R": 159,
                            "G": 157,
                            "B": 121
                        }
                    ]
                ]
            },
            {
                "blocks": [
                    [
                        {
                            "Pos": {
                                "X": 0,
                                "Y": 68
                            },
                            "Color": {
                                "R": 157,
                                "G": 123,
                                "B": 88
                            }
                        },
                        {
                            "Pos": {
                                "X": 12,
                                "Y": 68
                            },
                            "Color": {
                                "R": 157,
                                "G": 123,
                                "B": 88
                            }
                        },
                        {
                            "Pos": {
                                "X": 24,
                                "Y": 68
                            },
                            "Color": {
                                "R": 157,
                                "G": 123,
                                "B": 88
                            }
                        },
                        {
                            "Pos": {
                                "X": 36,
                                "Y": 68
                            },
                            "Color": {
                                "R": 157,
                                "G": 123,
                                "B": 88
                            }
                        },
                        {
                            "Pos": {
                                "X": 48,
                                "Y": 68
                            },
                            "Color": {
                                "R": 157,
                                "G": 123,
                                "B": 88
                            }
                        }
                    ]
                ],
                "isVisible": false,
                "used_colors": [
                    [
                        {
                            "R": 170,
                            "G": 163,
                            "B": 122
                        },
                        {
                            "R": 250,
                            "G": 200,
                            "B": 168
                        }
                    ]
                ]
            },
            {
                "blocks": [
                    [
                        {
                            "Pos": {
                                "X": 0,
                                "Y": 68
                            },
                            "Color": {
                                "R": 157,
                                "G": 123,
                                "B": 88
                            }
                        },
                        {
                            "Pos": {
                                "X": 12,
                                "Y": 68
                            },
                            "Color": {
                                "R": 157,
                                "G": 123,
                                "B": 88
                            }
                        },
                        {
                            "Pos": {
                                "X": 24,
                                "Y": 68
                            },
                            "Color": {
                                "R": 157,
                                "G": 123,
                                "B": 88
                            }
                        },
                        {
                            "Pos": {
                                "X": 36,
                                "Y": 68
                            },
                            "Color": {
                                "R": 157,
                                "G": 123,
                                "B": 88
                            }
                        },
                        {
                            "Pos": {
                                "X": 48,
                                "Y": 68
                            },
                            "Color": {
                                "R": 157,
                                "G": 123,
                                "B": 88
                            }
                        }
                    ]
                ],
                "isVisible": false,
                "used_colors": [
                    [
                        {
                            "R": 251,
                            "G": 206,
                            "B": 173
                        },
                        {
                            "R": 167,
                            "G": 170,
                            "B": 136
                        },
                        {
                            "R": 105,
                            "G": 81,
                            "B": 52
                        }
                    ]
                ]
            },
            {
                "blocks": [
                    [
                        {
                            "Pos": {
                                "X": 0,
                                "Y": 68
                            },
                            "Color": {
                                "R": 157,
                                "G": 123,
                                "B": 88
                            }
                        },
                        {
                            "Pos": {
                                "X": 12,
                                "Y": 68
                            },
                            "Color": {
                                "R": 157,
                                "G": 123,
                                "B": 88
                            }
                        },
                        {
                            "Pos": {
                                "X": 24,
                                "Y": 68
                            },
                            "Color": {
                                "R": 157,
                                "G": 123,
                                "B": 88
                            }
                        },
                        {
                            "Pos": {
                                "X": 36,
                                "Y": 68
                            },
                            "Color": {
                                "R": 157,
                                "G": 123,
                                "B": 88
                            }
                        },
                        {
                            "Pos": {
                                "X": 48,
                                "Y": 68
                            },
                            "Color": {
                                "R": 157,
                                "G": 123,
                                "B": 88
                            }
                        }
                    ]
                ],
                "isVisible": false,
                "used_colors": [
                    [
                        {
                            "R": 250,
                            "G": 206,
                            "B": 177
                        },
                        {
                            "R": 159,
                            "G": 172,
                            "B": 145
                        },
                        {
                            "R": 147,
                            "G": 114,
                            "B": 85
                        }
                    ]
                ]
            }
        ],
        [
            {
                "blocks": [
                    [
                        {
                            "Pos": {
                                "X": 0,
                                "Y": 68
                            },
                            "Color": {
                                "R": 157,
                                "G": 123,
                                "B": 88
                            }
                        },
                        {
                            "Pos": {
                                "X": 12,
                                "Y": 68
                            },
                            "Color": {
                                "R": 157,
                                "G": 123,
                                "B": 88
                            }
                        },
                        {
                            "Pos": {
                                "X": 24,
                                "Y": 68
                            },
                            "Color": {
                                "R": 157,
                                "G": 123,
                                "B": 88
                            }
                        },
                        {
                            "Pos": {
                                "X": 36,
                                "Y": 68
                            },
                            "Color": {
                                "R": 157,
                                "G": 123,
                                "B": 88
                            }
                        },
                        {
                            "Pos": {
                                "X": 48,
                                "Y": 68
                            },
                            "Color": {
                                "R": 157,
                                "G": 123,
                                "B": 88
                            }
                        }
                    ]
                ],
                "isVisible": false,
                "used_colors": [
                    [
                        {
                            "R": 116,
                            "G": 99,
                            "B": 67
                        },
                        {
                            "R": 186,
                            "G": 187,
                            "B": 155
                        },
                        {
                            "R": 160,
                            "G": 152,
                            "B": 115
                        }
                    ]
                ]
            },
            {
                "blocks": [
                    [
                        {
                            "Pos": {
                                "X": 0,
                                "Y": 68
                            },
                            "Color": {
                                "R": 157,
                                "G": 123,
                                "B": 88
                            }
                        },
                        {
                            "Pos": {
                                "X": 12,
                                "Y": 68
                            },
                            "Color": {
                                "R": 157,
                                "G": 123,
                                "B": 88
                            }
                        },
                        {
                            "Pos": {
                                "X": 24,
                                "Y": 68
                            },
                            "Color": {
                                "R": 157,
                                "G": 123,
                                "B": 88
                            }
                        },
                        {
                            "Pos": {
                                "X": 36,
                                "Y": 68
                            },
                            "Color": {
                                "R": 157,
                                "G": 123,
                                "B": 88
                            }
                        },
                        {
                            "Pos": {
                                "X": 48,
                                "Y": 68
                            },
                            "Color": {
                                "R": 157,
                                "G": 123,
                                "B": 88
                            }
                        }
                    ]
                ],
                "isVisible": false,
                "used_colors": [
                    [
                        {
                            "R": 177,
                            "G": 135,
                            "B": 95
                        },
                        {
                            "R": 175,
                            "G": 183,
                            "B": 153
                        }
                    ]
                ]
            },
            {
                "blocks": [
                    [
                        {
                            "Pos": {
                                "X": 0,
                                "Y": 68
                            },
                            "Color": {
                                "R": 157,
                                "G": 123,
                                "B": 88
                            }
                        },
                        {
                            "Pos": {
                                "X": 12,
                                "Y": 68
                            },
                            "Color": {
                                "R": 157,
                                "G": 123,
                                "B": 88
                            }
                        },
                        {
                            "Pos": {
                                "X": 24,
                                "Y": 68
                            },
                            "Color": {
                                "R": 157,
                                "G": 123,
                                "B": 88
                            }
                        },
                        {
                            "Pos": {
                                "X": 36,
                                "Y": 68
                            },
                            "Color": {
                                "R": 157,
                                "G": 123,
                                "B": 88
                            }
                        },
                        {
                            "Pos": {
                                "X": 48,
                                "Y": 68
                            },
                            "Color": {
                                "R": 157,
                                "G": 123,
                                "B": 88
                            }
                        }
                    ]
                ],
                "isVisible": false,
                "used_colors": [
                    [
                        {
                            "R": 169,
                            "G": 135,
                            "B": 97
                        },
                        {
                            "R": 179,
                            "G": 179,
                            "B": 145
                        }
                    ]
                ]
            },
            {
                "blocks": [
                    [
                        {
                            "Pos": {
                                "X": 0,
                                "Y": 68
                            },
                            "Color": {
                                "R": 157,
                                "G": 123,
                                "B": 88
                            }
                        },
                        {
                            "Pos": {
                                "X": 12,
                                "Y": 68
                            },
                            "Color": {
                                "R": 157,
                                "G": 123,
                                "B": 88
                            }
                        },
                        {
                            "Pos": {
                                "X": 24,
                                "Y": 68
                            },
                            "Color": {
                                "R": 157,
                                "G": 123,
                                "B": 88
                            }
                        },
                        {
                            "Pos": {
                                "X": 36,
                                "Y": 68
                            },
                            "Color": {
                                "R": 157,
                                "G": 123,
                                "B": 88
                            }
                        },
                        {
                            "Pos": {
                                "X": 48,
                                "Y": 68
                            },
                            "Color": {
                                "R": 157,
                                "G": 123,
                                "B": 88
                            }
                        }
                    ]
                ],
                "isVisible": false,
                "used_colors": [
                    [
                        {
                            "R": 157,
                            "G": 123,
                            "B": 88
                        },
                        {
                            "R": 170,
                            "G": 168,
                            "B": 137
                        }
                    ]
                ]
            }
        ]
    ]
}