{
    "originSize": {
        "height": 192,
        "width": 250
    },
    "sections": [
        [
            {
                "blocks": [
                    [
                        {
                            "Pos": {
                                "X": 0,
                                "Y": 36
                            },
                            "Color": {
                                "R": 140,
                                "G": 151,
                                "B": 173
                            }
                        },
                        {
                            "Pos": {
                                "X": 12,
                                "Y": 36
                            },
                            "Color": {
                                "R": 140,
                                "G": 151,
                                "B": 173
                            }
                        },
                        {
                            "Pos": {
                                "X": 24,
                                "Y": 36
                            },
                            "Color": {
                                "R": 140,
                                "G": 151,
                                "B": 173
                            }
                        },
                        {
                            "Pos": {
                                "X": 36,
                                "Y": 36
                            },
                            "Color": {
                                "R": 140,
                                "G": 151,
                                "B": 173
                            }
                        },
                        {
                            "Pos": {
                                "X": 48,
                                "Y": 36
                            },
                            "Color": {
                                "R": 140,
                                "G": 151,
                                "B": 173
                            }
                        }
                    ]
                ],
                "isVisible": false,
                "used_colors": [
                    [
                        {
                            "R": 180,
                            "G": 177,
                            "B": 184
                        },
                        {
                            "R": 98,
                            "G": 150,
                            "B": 195
                        }
                    ]
                ]
            },
            {
                "blocks": [
                    [
                        {
                            "Pos": {
                                "X": 0,
                                "Y": 36
                            },
                            "Color": {
                                "R": 140,
                                "G": 151,
                                "B": 173
                            }
                        },
                        {
                            "Pos": {
                                "X": 12,
                                "Y": 36
                            },
                            "Color": {
                                "R": 140,
                                "G": 151,
                                "B": 173
                            }
                        },
                        {
                            "Pos": {
                                "X": 24,
                                "Y": 36
                            },
                            "Color": {
                                "R": 140,
                                "G": 151,
                                "B": 173
                            }
                        },
                        {
                            "Pos": {
                                "X": 36,
                                "Y": 36
                            },
                            "Color": {
                                "R": 140,
                                "G": 151,
                                "B": 173
                            }
                        },
                        {
                            "Pos": {
                                "X": 48,
                                "Y": 36
                            },
                            "Color": {
                                "R": 140,
                                "G": 151,
                                "B": 173
                            }
                        }
                    ]
                ],
                "isVisible": false,
                "used_colors": [
                    [
                        {
                            "R": 99,
                            "G": 150,
                            "B": 197
                        },
                        {
                            "R": 181,
                            "G": 176,
                            "B": 183
                        },
                        {
                            "R": 153,
                            "G": 150,
                            "B": 161
                        }
                    ]
                ]
            },
            {
                "blocks": [
                    [
                        {
                            "Pos": {
                                "X": 0,
                                "Y": 36
                            },
                            "Color": {
                                "R": 140,
                                "G": 151,
                                "B": 173
                            }
                        },
                        {
                            "Pos": {
                                "X": 12,
                                "Y": 36
                            },
                            "Color": {
                                "R": 140,
                                "G": 151,
                                "B": 173
                            }
                        },
                        {
                            "Pos": {
                                "X": 24,
                                "Y": 36
                            },
                            "Color": {
                                "R": 140,
                                "G": 151,
                                "B": 173
                            }
                        },
                        {
                            "Pos": {
                                "X": 36,
                                "Y": 36
                            },
                            "Color": {
                                "R": 140,
                                "G": 151,
                                "B": 173
                            }
                        },
                        {
                            "Pos": {
                                "X": 48,
                                "Y": 36
                            },
                            "Color": {
                                "R": 140,
                                "G": 151,
                                "B": 173
                            }
                        }
                    ]
                ],
                "isVisible": false,
                "used_colors": [
                    [
                        {
                            "R": 178,
                            "G": 177,
                            "B": 183
                        },
                        {
                            "R": 142,
                            "G": 141,
                            "B": 146
                        },
                        {
                            "R": 111,
                            "G": 151,
                            "B": 190
                        }
                    ]
                ]
            },
            {
                "blocks": [
                    [
                        {
                            "Pos": {
                                "X": 0,
                                "Y": 36
                            },
                            "Color": {
                                "R": 140,
                                "G": 151,
                                "B": 173
                            }
                        },
                        {
                            "Pos": {
                                "X": 12,
                                "Y": 36
                            },
                            "Color": {
                                "R": 140,
                                "G": 151,
                                "B": 173
                            }
                        },
                        {
                            "Pos": {
                                "X": 24,
                                "Y": 36
                            },
                            "Color": {
                                "R": 140,
                                "G": 151,
                                "B": 173
                            }
                        },
                        {
                            "Pos": {
                                "X": 36,
                                "Y": 36
                            },
                            "Color": {
                                "R": 140,
                                "G": 151,
                                "B": 173
                            }
                        },
                        {
                            "Pos": {
                                "X": 48,
                                "Y": 36
                            },
                            "Color": {
                                "R": 140,
                                "G": 151,
                                "B": 173
                            }
                        }
                    ]
                ],
                "isVisible": false,
                "used_colors": [
                    [
                        {
                            "R": 179,
                            "G": 176,
                            "B": 182
                        },
                        {
                            "R": 116,
                            "G": 153,
                            "B": 190
                        }
                    ]
                ]
            }
        ],
        [
            {
                "blocks": [
                    [
                        {
                            "Pos": {
                                "X": 0,
                                "Y": 36
                            },
                            "Color": {
                                "R": 140,
                                "G": 151,
                                "B": 173
                            }
                        },
                        {
                            "Pos": {
                                "X": 12,
                                "Y": 36
                            },
                            "Color": {
                                "R": 140,
                                "G": 151,
                                "B": 173
                            }
                        },
                        {
                            "Pos": {
                                "X": 24,
                                "Y": 36
                            },
                            "Color": {
                                "R": 140,
                                "G": 151,
                                "B": 173
                            }
                        },
                        {
                            "Pos": {
                                "X": 36,
                                "Y": 36
                            },
                            "Color": {
                                "R": 140,
                                "G": 151,
                                "B": 173
                            }
                        },
                        {
                            "Pos": {
                                "X": 48,
                                "Y": 36
                            },
                            "Color": {
                                "R": 140,
                                "G": 151,
                                "B": 173
                            }
                        }
                    ]
                ],
                "isVisible": false,
                "used_colors": [
                    [
                        {
                            "R": 130,
                            "G": 163,
                            "B": 194
                        },
                        {
                            "R": 184,
                            "G": 178,
                            "B": 190
                        }
                    ]
                ]
            },
            {
                "blocks": [
                    [
                        {
                            "Pos": {
                                "X": 0,
                                "Y": 36
                            },
                            "Color": {
                                "R": 140,
                                "G": 151,
                                "B": 173
                            }
                        },
                        {
                            "Pos": {
                                "X": 12,
                                "Y": 36
                            },
                            "Color": {
                                "R": 140,
                                "G": 151,
                                "B": 173
                            }
                        },
                        {
                            "Pos": {
                                "X": 24,
                                "Y": 36
                            },
                            "Color": {
                                "R": 140,
                                "G": 151,
                                "B": 173
                            }
                        },
                        {
                            "Pos": {
                                "X": 36,
                                "Y": 36
                            },
                            "Color": {
                                "R": 140,
                                "G": 151,
                                "B": 173
                            }
                        },
                        {
                            "Pos": {
                                "X": 48,
                                "Y": 36
                            },
                            "Color": {
                                "R": 140,
                                "G": 151,
                                "B": 173
                            }
                        }
                    ]
                ],
                "isVisible": false,
                "used_colors": [
                    [
                        {
                            "R": 128,
                            "G": 153,
                            "B": 184
                        },
                        {
                            "R": 182,
                            "G": 179,
                            "B": 189
                        }
                    ]
                ]
            },
            {
                "blocks": [
                    [
                        {
                            "Pos": {
                                "X": 0,
                                "Y": 36
                            },
                            "Color": {
                                "R": 140,
                                "G": 151,
                                "B": 173
                            }
                        },
                        {
                            "Pos": {
                                "X": 12,
                                "Y": 36
                            },
                            "Color": {
                                "R": 140,
                                "G": 151,
                                "B": 173
                            }
                        },
                        {
                            "Pos": {
                                "X": 24,
                                "Y": 36
                            },
                            "Color": {
                                "R": 140,
                                "G": 151,
                                "B": 173
                            }
                        },
                        {
                            "Pos": {
                                "X": 36,
                                "Y": 36
                            },
                            "Color": {
                                "R": 140,
                                "G": 151,
                                "B": 173
                            }
                        },
                        {
                            "Pos": {
                                "X": 48,
                                "Y": 36
                            },
                            "Color": {
                                "R": 140,
                                "G": 151,
                                "B": 173
                            }
                        }
                    ]
                ],
                "isVisible": false,
                "used_colors": [
                    [
                        {
                            "R": 155,
                            "G": 162,
                            "B": 182
                        },
                        {
                            "R": 199,
                            "G": 194,
                            "B": 200
                        }
                    ]
                ]
            },
            {
                "blocks": [
                    [
                        {
                            "Pos": {
                                "X": 0,
                                "Y": 36
                            },
                            "Color": {
                                "R": 140,
                                "G": 151,
                                "B": 173
                            }
                        },
                        {
                            "Pos": {
                                "X": 12,
                                "Y": 36
                            },
                            "Color": {
                                "R": 140,
                                "G": 151,
                                "B": 173
                            }
                        },
                        {
                            "Pos": {
                                "X": 24,
                                "Y": 36
                            },
                            "Color": {
                                "R": 140,
                                "G": 151,
                                "B": 173
                            }
                        },
                        {
                            "Pos": {
                                "X": 36,
                                "Y": 36
                            },
                            "Color": {
                                "R": 140,
                                "G": 151,
                                "B": 173
                            }
                        },
                        {
                            "Pos": {
                                "X": 48,
                                "Y": 36
                            },
                            "Color": {
                                "R": 140,
                                "G": 151,
                                "B": 173
                            }
                        }
                    ]
                ],
                "isVisible": false,
                "used_colors": [
                    [
                        {
                            "R": 134,
                            "G": 152,
                            "B": 182
                        },
                        {
                            "R": 190,
                            "G": 189,
                            "B": 195
                        }
                    ]
                ]
            }
        ],
        [
            {
                "blocks": [
                    [
                        {
                            "Pos": {
                                "X": 0,
                                "Y": 36
                            },
                            "Color": {
                                "R": 140,
                                "G": 151,
                                "B": 173
                            }
                        },
                        {
                            "Pos": {
                                "X": 12,
                                "Y": 36
                            },
                            "Color": {
                                "R": 140,
                                "G": 151,
                                "B": 173
                            }
                        },
                        {
                            "Pos": {
                                "X": 24,
                                "Y": 36
                            },
                            "Color": {
                                "R": 140,
                                "G": 151,
                                "B": 173
                            }
                        },
                        {
                            "Pos": {
                                "X": 36,
                                "Y": 36
                            },
                            "Color": {
                                "R": 140,
                                "G": 151,
                                "B": 173
                            }
                        },
                        {
                            "Pos": {
                                "X": 48,
                                "Y": 36
                            },
                            "Color": {
                                "R": 140,
                                "G": 151,
                                "B": 173
                            }
                        }
                    ]
                ],
                "isVisible": false,
                "used_colors": [
                    [
                        {
                            "R": 155,
                            "G": 161,
                            "B": 180
                        },
                        {
                            "R": 29,
                            "G": 83,
                            "B": 120
                        },
                        {
                            "R": 67,
                            "G": 128,
                            "B": 183
                        }
                    ]
                ]
            },
            {
                "blocks": [
                    [
                        {
                            "Pos": {
                                "X": 0,
                                "Y": 36
                            },
                            "Color": {
                                "R": 140,
                                "G": 151,
                                "B": 173
                            }
                        },
                        {
                            "Pos": {
                                "X": 12,
                                "Y": 36
                            },
                            "Color": {
                                "R": 140,
                                "G": 151,
                                "B": 173
                            }
                        },
                        {
                            "Pos": {
                                "X": 24,
                                "Y": 36
                            },
                            "Color": {
                                "R": 140,
                                "G": 151,
                                "B": 173
                            }
                        },
                        {
                            "Pos": {
                                "X": 36,
                                "Y": 36
                            },
                            "Color": {
                                "R": 140,
                                "G": 151,
                                "B": 173
                            }
                        },
                        {
                            "Pos": {
                                "X": 48,
                                "Y": 36
                            },
                            "Color": {
                                "R": 140,
                                "G": 151,
                                "B": 173
                            }
                        }
                    ]
                ],
                "isVisible": false,
                "used_colors": [
                    [
                        {
                            "R": 149,
                            "G": 157,
                            "B": 178
                        },
                        {
                            "R": 40,
                            "G": 66,
                            "B": 76
                        },
                        {
                            "R": 59,
                            "G": 126,
                            "B": 179
                        }
                    ]
                ]
            },
            {
                "blocks": [
                    [
                        {
                            "Pos": {
                                "X": 0,
                                "Y": 36
                            },
                            "Color": {
                                "R": 140,
                                "G": 151,
                                "B": 173
                            }
                        },
                        {
                            "Pos": {
                                "X": 12,
                                "Y": 36
                            },
                            "Color": {
                                "R": 140,
                                "G": 151,
                                "B": 173
                            }
                        },
                        {
                            "Pos": {
                                "X": 24,
                                "Y": 36
                            },
                            "Color": {
                                "R": 140,
                                "G": 151,
                                "B": 173
                            }
                        },
                        {
                            "Pos": {
                                "X": 36,
                                "Y": 36
                            },
                            "Color": {
                                "R": 140,
                                "G": 151,
                                "B": 173
                            }
                        },
                        {
                            "Pos": {
                                "X": 48,
                                "Y": 36
                            },
                            "Color": {
                                "R": 140,
                                "G": 151,
                                "B": 173
                            }
                        }
                    ]
                ],
                "isVisible": false,
                "used_colors": [
                    [
                        {
                            "R": 168,
                            "G": 179,
                            "B": 196
                        },
                        {
                            "R": 56,
                            "G": 91,
                            "B": 122
                        },
                        {
                            "R": 114,
                            "G": 142,
                            "B": 177
                        }
                    ]
                ]
            },
            {
                "blocks": [
                    [
                        {
                            "Pos": {
                                "X": 0,
                                "Y": 36
                            },
                            "Color": {
                                "R": 140,
                                "G": 151,
                                "B": 173
                            }
                        },
                        {
                            "Pos": {
                                "X": 12,
                                "Y": 36
                            },
                            "Color": {
                                "R": 140,
                                "G": 151,
                                "B": 173
                            }
                        },
                        {
                            "Pos": {
                                "X": 24,
                                "Y": 36
                            },
                            "Color": {
                                "R": 140,
                                "G": 151,
                                "B": 173
                            }
                        },
                        {
                            "Pos": {
                                "X": 36,
                                "Y": 36
                            },
                            "Color": {
                                "R": 140,
                                "G": 151,
                                "B": 173
                            }
                        },
                        {
                            "Pos": {
                                "X": 48,
                                "Y": 36
                            },
                            "Color": {
                                "R": 140,
                                "G": 151,
                                "B": 173
                            }
                        }
                    ]
                ],
                "isVisible": false,
                "used_colors": [
                    [
                        {
                            "R": 140,
                            "G": 152,
                            "B": 175
                        },
                        {
                            "R": 56,
                            "G": 83,
                            "B": 113
                        },
                        {
                            "R": 93,
                            "G": 124,
                            "B": 165
                        }
                    ]
                ]
            }
        ],
        [
            {
                "blocks": [
                    [
                        {
                            "Pos": {
                                "X": 0,
                                "Y": 36
                            },
                            "Color": {
                                "R": 140,
                                "G": 151,
                                "B": 173
                            }
                        },
                        {
                            "Pos": {
                                "X": 12,
                                "Y": 36
                            },
                            "Color": {
                                "R": 140,
                                "G": 151,
                                "B": 173
                            }
                        },
                        {
                            "Pos": {
                                "X": 24,
                                "Y": 36
                            },
                            "Color": {
                                "R": 140,
                                "G": 151,
                                "B": 173
                            }
                        },
                        {
                            "Pos": {
                                "X": 36,
                                "Y": 36
                            },
                            "Color": {
                                "R": 140,
                                "G": 151,
                                "B": 173
                            }
                        },
                        {
                            "Pos": {
                                "X": 48,
                                "Y": 36
                            },
                            "Color": {
                                "R": 140,
                                "G": 151,
                                "B": 173
                            }
                        }
                    ]
                ],
                "isVisible": false,
                "used_colors": [
                    [
                        {
                            "R": 82,
                            "G": 127,
                            "B": 166
                        },
                        {
                            "R": 145,
                            "G": 157,
                            "B": 170
                        }
                    ]
                ]
            },
            {
                "blocks": [
                    [
                        {
                            "Pos": {
                                "X": 0,
                                "Y": 36
                            },
                            "Color": {
                                "R": 140,
                                "G": 151,
                                "B": 173
                            }
                        },
                        {
                            "Pos": {
                                "X": 12,
                                "Y": 36
                            },
                            "Color": {
                                "R": 140,
                                "G": 151,
                                "B": 173
                            }
                        },
                        {
                            "Pos": {
                                "X": 24,
                                "Y": 36
                            },
                            "Color": {
                                "R": 140,
                                "G": 151,
                                "B": 173
                            }
                        },
                        {
                            "Pos": {
                                "X": 36,
                                "Y": 36
                            },
                            "Color": {
                                "R": 140,
                                "G": 151,
                                "B": 173
                            }
                        },
                        {
                            "Pos": {
                                "X": 48,
                                "Y": 36
                            },
                            "Color": {
                                "R": 140,
                                "G": 151,
                                "B": 173
                            }
                        }
                    ]
                ],
                "isVisible": false,
                "used_colors": [
                    [
                        {
                            "R": 55,
                            "G": 110,
                            "B": 149
                        },
                        {
                            "R": 173,
                            "G": 173,
                            "B": 181
                        },
                        {
                            "R": 105,
                            "G": 150,
                            "B": 185
                        }
                    ]
                ]
            },
            {
                "blocks": [
                    [
                        {
                            "Pos": {
                                "X": 0,
                                "Y": 36
                            },
                            "Color": {
                                "R": 140,
                                "G": 151,
                                "B": 173
                            }
                        },
                        {
                            "Pos": {
                                "X": 12,
                                "Y": 36
                            },
                            "Color": {
                                "R": 140,
                                "G": 151,
                                "B": 173
                            }
                        },
                        {
                            "Pos": {
                                "X": 24,
                                "Y": 36
                            },
                            "Color": {
                                "R": 140,
                                "G": 151,
                                "B": 173
                            }
                        },
                        {
                            "Pos": {
                                "X": 36,
                                "Y": 36
                            },
                            "Color": {
                                "R": 140,
                                "G": 151,
                                "B": 173
                            }
                        },
                        {
                            "Pos": {
                                "X": 48,
                                "Y": 36
                            },
                            "Color": {
                                "R": 140,
                                "G": 151,
                                "B": 173
                            }
                        }
                    ]
                ],
                "isVisible": false,
                "used_colors": [
                    [
                        {
                            "R": 150,
                            "G": 154,
                            "B": 168
                        },
                        {
                            "R": 83,
                            "G": 128,
                            "B": 175
                        }
                    ]
                ]
            },
            {
                "blocks": [
                    [
                        {
                            "Pos": {
                                "X": 0,
                                "Y": 36
                            },
                            "Color": {
                                "R": 140,
                                "G": 151,
                                "B": 173
                            }
                        },
                        {
                            "Pos": {
                                "X": 12,
                                "Y": 36
                            },
                            "Color": {
                                "R": 140,
                                "G": 151,
                                "B": 173
                            }
                        },
                        {
                            "Pos": {
                                "X": 24,
                                "Y": 36
                            },
                            "Color": {
                                "R": 140,
                                "G": 151,
                                "B": 173
                            }
                        },
                        {
                            "Pos": {
                                "X": 36,
                                "Y": 36
                            },
                            "Color": {
                                "R": 140,
                                "G": 151,
                                "B": 173
                            }
                        },
                        {
                            "Pos": {
                                "X": 48,
                                "Y": 36
                            },
                            "Color": {
                                "R": 140,
                                "G": 151,
                                "B": 173
                            }
                        }
                    ]
                ],
                "isVisible": true,
                "used_colors": [
                    [
                        {
                            "R": 140,
                            "G": 151,
                            "B": 173
                        }
                    ]
                ]
            }
        ]
    ]
}