{
    "originSize": {
        "height": 300,
        "width": 250
    },
    "sections": [
        [
            {
                "blocks": [
                    [
                        {
                            "Pos": {
                                "X": 0,
                                "Y": 60
                            },
                            "Color": {
                                "R": 176,
                                "G": 160,
                                "B": 114
                            }
                        },
                        {
                            "Pos": {
                                "X": 12,
                                "Y": 60
                            },
                            "Color": {
                                "R": 176,
                                "G": 160,
                                "B": 114
                            }
                        },
                        {
                            "Pos": {
                                "X": 24,
                                "Y": 60
                            },
                            "Color": {
                                "R": 128,
                                "G": 116,
                                "B": 85
                            }
                        },
                        {
                            "Pos": {
                                "X": 36,
                                "Y": 60
                            },
                            "Color": {
                                "R": 176,
                                "G": 160,
                                "B": 114
                            }
                        },
                        {
                            "Pos": {
                                "X": 48,
                                "Y": 60
                            },
                            "Color": {
                                "R": 176,
                                "G": 160,
                                "B": 114
                            }
                        }
                    ]
                ],
                "isVisible": false,
                "used_colors": [
                    [
                        {
                            "R": 134,
                            "G": 114,
                            "B": 82
                        },
                        {
                            "R": 182,
                            "G": 160,
                            "B": 110
                        }
                    ]
                ]
            },
            {
                "blocks": [
                    [
                        {
                            "Pos": {
                                "X": 0,
                                "Y": 60
                            },
                            "Color": {
                                "R": 176,
                                "G": 160,
                                "B": 114
                            }
                        },
                        {
                            "Pos": {
                                "X": 12,
                                "Y": 60
                            },
                            "Color": {
                                "R": 176,
                                "G": 160,
                                "B": 114
                            }
                        },
                        {
                            "Pos": {
                                "X": 24,
                                "Y": 60
                            },
                            "Color": {
                                "R": 128,
                                "G": 116,
                                "B": 85
                            }
                        },
                        {
                            "Pos": {
                                "X": 36,
                                "Y": 60
                            },
                            "Color": {
                                "R": 176,
                                "G": 160,
                                "B": 114
                            }
                        },
                        {
                            "Pos": {
                                "X": 48,
                                "Y": 60
                            },
                            "Color": {
                                "R": 176,
                                "G": 160,
                                "B": 114
                            }
                        }
                    ]
                ],
                "isVisible": false,
                "used_colors": [
                    [
                        {
                            "R": 112,
                            "G": 35,
                            "B": 25
                        },
                        {
                            "R": 165,
                            "G": 140,
                            "B": 101
                        },
                        {
                            "R": 116,
                            "G": 108,
                            "B": 85
                        }
                    ]
                ]
            },
            {
                "blocks": [
                    [
                        {
                            "Pos": {
                                "X": 0,
                                "Y": 60
                            },
                            "Color": {
                                "R": 176,
                                "G": 160,
                                "B": 114
                            }
                        },
                        {
                            "Pos": {
                                "X": 12,
                                "Y": 60
                            },
                            "Color": {
                                "R": 176,
                                "G": 160,
                                "B": 114
                            }
                        },
                        {
                            "Pos": {
                                "X": 24,
                                "Y": 60
                            },
                            "Color": {
                                "R": 128,
                                "G": 116,
                                "B": 85
                            }
                        },
                        {
                            "Pos": {
                                "X": 36,
                                "Y": 60
                            },
                            "Color": {
                                "R": 176,
                                "G": 160,
                                "B": 114
                            }
                        },
                        {
                            "Pos": {
                                "X": 48,
                                "Y": 60
                            },
                            "Color": {
                                "R": 176,
                                "G": 160,
                                "B": 114
                            }
                        }
                    ]
                ],
                "isVisible": false,
                "used_colors": [
                    [
                        {
                            "R": 111,
                            "G": 104,
                            "B": 70
                        },
                        {
                            "R": 163,
                            "G": 142,
                            "B": 112
                        },
                        {
                            "R": 42,
                            "G": 46,
                            "B": 28
                        }
                    ]
                ]
            },
            {
                "blocks": [
                    [
                        {
                            "Pos": {
                                "X": 0,
                                "Y": 60
                            },
                            "Color": {
                                "R": 176,
                                "G": 160,
                                "B": 114
                            }
                        },
                        {
                            "Pos": {
                                "X": 12,
                                "Y": 60
                            },
                            "Color": {
                                "R": 176,
                                "G": 160,
                                "B": 114
                            }
                        },
                        {
                            "Pos": {
                                "X": 24,
                                "Y": 60
                            },
                            "Color": {
                                "R": 128,
                                "G": 116,
                                "B": 85
                            }
                        },
                        {
                            "Pos": {
                                "X": 36,
                                "Y": 60
                            },
                            "Color": {
                                "R": 176,
                                "G": 160,
                                "B": 114
                            }
                        },
                        {
                            "Pos": {
                                "X": 48,
                                "Y": 60
                            },
                            "Color": {
                                "R": 176,
                                "G": 160,
                                "B": 114
                            }
                        }
                    ]
                ],
                "isVisible": false,
                "used_colors": [
                    [
                        {
                            "R": 174,
                            "G": 157,
                            "B": 117
                        },
                        {
                            "R": 122,
                            "G": 108,
                            "B": 79
                        }
                    ]
                ]
            }
        ],
        [
            {
                "blocks": [
                    [
                        {
                            "Pos": {
                                "X": 0,
                                "Y": 60
                            },
                            "Color": {
                                "R": 176,
                                "G": 160,
                                "B": 114
                            }
                        },
                        {
                            "Pos": {
                                "X": 12,
                                "Y": 60
                            },
                            "Color": {
                                "R": 176,
                                "G": 160,
                                "B": 114
                            }
                        },
                        {
                            "Pos": {
                                "X": 24,
                                "Y": 60
                            },
                            "Color": {
                                "R": 128,
                                "G": 116,
                                "B": 85
                            }
                        },
                        {
                            "Pos": {
                                "X": 36,
                                "Y": 60
                            },
                            "Color": {
                                "R": 176,
                                "G": 160,
                                "B": 114
                            }
                        },
                        {
                            "Pos": {
                                "X": 48,
                                "Y": 60
                            },
                            "Color": {
                                "R": 176,
                                "G": 160,
                                "B": 114
                            }
                        }
                    ]
                ],
                "isVisible": false,
                "used_colors": [
                    [
                        {
                            "R": 119,
                            "G": 41,
                            "B": 31
                        },
                        {
                            "R": 130,
                            "G": 115,
                            "B": 85
                        },
                        {
                            "R": 187,
                            "G": 170,
                            "B": 144
                        }
                    ]
                ]
            },
            {
                "blocks": [
                    [
                        {
                            "Pos": {
                                "X": 0,
                                "Y": 60
                            },
                            "Color": {
                                "R": 176,
                                "G": 160,
                                "B": 114
                            }
                        },
                        {
                            "Pos": {
                                "X": 12,
                                "Y": 60
                            },
                            "Color": {
                                "R": 176,
                                "G": 160,
                                "B": 114
                            }
                        },
                        {
                            "Pos": {
                                "X": 24,
                                "Y": 60
                            },
                            "Color": {
                                "R": 128,
                                "G": 116,
                                "B": 85
                            }
                        },
                        {
                            "Pos": {
                                "X": 36,
                                "Y": 60
                            },
                            "Color": {
                                "R": 176,
                                "G": 160,
                                "B": 114
                            }
                        },
                        {
                            "Pos": {
                                "X": 48,
                                "Y": 60
                            },
                            "Color": {
                                "R": 176,
                                "G": 160,
                                "B": 114
                            }
                        }
                    ]
                ],
                "isVisible": false,
                "used_colors": [
                    [
                        {
                            "R": 40,
                            "G": 43,
                            "B": 23
                        },
                        {
                            "R": 171,
                            "G": 104,
                            "B": 112
                        },
                        {
                            "R": 157,
                            "G": 63,
                            "B": 10
                        }
                    ]
                ]
            },
            {
                "blocks": [
                    [
                        {
                            "Pos": {
                                "X": 0,
                                "Y": 60
                            },
                            "Color": {
                                "R": 176,
                                "G": 160,
                                "B": 114
                            }
                        },
                        {
                            "Pos": {
                                "X": 12,
                                "Y": 60
                            },
                            "Color": {
                                "R": 176,
                                "G": 160,
                                "B": 114
                            }
                        },
                        {
                            "Pos": {
                                "X": 24,
                                "Y": 60
                            },
                            "Color": {
                                "R": 128,
                                "G": 116,
                                "B": 85
                            }
                        },
                        {
                            "Pos": {
                                "X": 36,
                                "Y": 60
                            },
                            "Color": {
                                "R": 176,
                                "G": 160,
                                "B": 114
                            }
                        },
                        {
                            "Pos": {
                                "X": 48,
                                "Y": 60
                            },
                            "Color": {
                                "R": 176,
                                "G": 160,
                                "B": 114
                            }
                        }
                    ]
                ],
                "isVisible": false,
                "used_colors": [
                    [
                        {
                            "R": 134,
                            "G": 87,
                            "B": 100
                        },
                        {
                            "R": 63,
                            "G": 73,
                            "B": 61
                        },
                        {
                            "R": 143,
                            "G": 62,
                            "B": 9
                        },
                        {
                            "R": 162,
                            "G": 140,
                            "B": 111
                        }
                    ]
                ]
            },
            {
                "blocks": [
                    [
                        {
                            "Pos": {
                                "X": 0,
                                "Y": 60
                            },
                            "Color": {
                                "R": 176,
                                "G": 160,
                                "B": 114
                            }
                        },
                        {
                            "Pos": {
                                "X": 12,
                                "Y": 60
                            },
                            "Color": {
                                "R": 176,
                                "G": 160,
                                "B": 114
                            }
                        },
                        {
                            "Pos": {
                                "X": 24,
                                "Y": 60
                            },
                            "Color": {
                                "R": 128,
                                "G": 116,
                                "B": 85
                            }
                        },
                        {
                            "Pos": {
                                "X": 36,
                                "Y": 60
                            },
                            "Color": {
                                "R": 176,
                                "G": 160,
                                "B": 114
                            }
                        },
                        {
                            "Pos": {
                                "X": 48,
                                "Y": 60
                            },
                            "Color": {
                                "R": 176,
                                "G": 160,
                                "B": 114
                            }
                        }
                    ]
                ],
                "isVisible": false,
                "used_colors": [
                    [
                        {
                            "R": 160,
                            "G": 144,
                            "B": 124
                        },
                        {
                            "R": 63,
                            "G": 92,
                            "B": 64
                        },
                        {
                            "R": 112,
                            "G": 79,
                            "B": 96
                        }
                    ]
                ]
            }
        ],
        [
            {
                "blocks": [
                    [
                        {
                            "Pos": {
                                "X": 0,
                                "Y": 60
                            },
                            "Color": {
                                "R": 176,
                                "G": 160,
                                "B": 114
                            }
                        },
                        {
                            "Pos": {
                                "X": 12,
                                "Y": 60
                            },
                            "Color": {
                                "R": 176,
                                "G": 160,
                                "B": 114
                            }
                        },
                        {
                            "Pos": {
                                "X": 24,
                                "Y": 60
                            },
                            "Color": {
                                "R": 128,
                                "G": 116,
                                "B": 85
                            }
                        },
                        {
                            "Pos": {
                                "X": 36,
                                "Y": 60
                            },
                            "Color": {
                                "R": 176,
                                "G": 160,
                                "B": 114
                            }
                        },
                        {
                            "Pos": {
                                "X": 48,
                                "Y": 60
                            },
                            "Color": {
                                "R": 176,
                                "G": 160,
                                "B": 114
                            }
                        }
                    ]
                ],
                "isVisible": false,
                "used_colors": [
                    [
                        {
                            "R": 156,
                            "G": 139,
                            "B": 106
                        },
                        {
                            "R": 92,
                            "G": 94,
                            "B": 59
                        }
                    ]
                ]
            },
            {
                "blocks": [
                    [
                        {
                            "Pos": {
                                "X": 0,
                                "Y": 60
                            },
                            "Color": {
                                "R": 176,
                                "G": 160,
                                "B": 114
                            }
                        },
                        {
                            "Pos": {
                                "X": 12,
                                "Y": 60
                            },
                            "Color": {
                                "R": 176,
                                "G": 160,
                                "B": 114
                            }
                        },
                        {
                            "Pos": {
                                "X": 24,
                                "Y": 60
                            },
                            "Color": {
                                "R": 128,
                                "G": 116,
                                "B": 85
                            }
                        },
                        {
                            "Pos": {
                                "X": 36,
                                "Y": 60
                            },
                            "Color": {
                                "R": 176,
                                "G": 160,
                                "B": 114
                            }
                        },
                        {
                            "Pos": {
                                "X": 48,
                                "Y": 60
                            },
                            "Color": {
                                "R": 176,
                                "G": 160,
                                "B": 114
                            }
                        }
                    ]
                ],
                "isVisible": false,
                "used_colors": [
                    [
                        {
                            "R": 64,
                            "G": 37,
                            "B": 15
                        },
                        {
                            "R": 41,
                            "G": 63,
                            "B": 81
                        },
                        {
                            "R": 125,
                            "G": 108,
                            "B": 72
                        },
                        {
                            "R": 161,
                            "G": 144,
                            "B": 118
                        }
                    ]
                ]
            },
            {
                "blocks": [
                    [
                        {
                            "Pos": {
                                "X": 0,
                                "Y": 60
                            },
                            "Color": {
                                "R": 176,
                                "G": 160,
                                "B": 114
                            }
                        },
                        {
                            "Pos": {
                                "X": 12,
                                "Y": 60
                            },
                            "Color": {
                                "R": 176,
                                "G": 160,
                                "B": 114
                            }
                        },
                        {
                            "Pos": {
                                "X": 24,
                                "Y": 60
                            },
                            "Color": {
                                "R": 128,
                                "G": 116,
                                "B": 85
                            }
                        },
                        {
                            "Pos": {
                                "X": 36,
                                "Y": 60
                            },
                            "Color": {
                                "R": 176,
                                "G": 160,
                                "B": 114
                            }
                        },
                        {
                            "Pos": {
                                "X": 48,
                                "Y": 60
                            },
                            "Color": {
                                "R": 176,
                                "G": 160,
                                "B": 114
                            }
                        }
                    ]
                ],
                "isVisible": false,
                "used_colors": [
                    [
                        {
                            "R": 53,
                            "G": 33,
                            "B": 9
                        },
                        {
                            "R": 137,
                            "G": 126,
                            "B": 104
                        },
                        {
                            "R": 63,
                            "G": 82,
                            "B": 94
                        }
                    ]
                ]
            },
            {
                "blocks": [
                    [
                        {
                            "Pos": {
                                "X": 0,
                                "Y": 60
                            },
                            "Color": {
                                "R": 176,
                                "G": 160,
                                "B": 114
                            }
                        },
                        {
                            "Pos": {
                                "X": 12,
                                "Y": 60
                            },
                            "Color": {
                                "R": 176,
                                "G": 160,
                                "B": 114
                            }
                        },
                        {
                            "Pos": {
                                "X": 24,
                                "Y": 60
                            },
                            "Color": {
                                "R": 128,
                                "G": 116,
                                "B": 85
                            }
                        },
                        {
                            "Pos": {
                                "X": 36,
                                "Y": 60
                            },
                            "Color": {
                                "R": 176,
                                "G": 160,
                                "B": 114
                            }
                        },
                        {
                            "Pos": {
                                "X": 48,
                                "Y": 60
                            },
                            "Color": {
                                "R": 176,
                                "G": 160,
                                "B": 114
                            }
                        }
                    ]
                ],
                "isVisible": false,
                "used_colors": [
                    [
                        {
                            "R": 166,
                            "G": 149,
                            "B": 123
                        },
                        {
                            "R": 112,
                            "G": 111,
                            "B": 78
                        },
                        {
                            "R": 165,
                            "G": 134,
                            "B": 57
                        }
                    ]
                ]
            }
        ],
        [
            {
                "blocks": [
                    [
                        {
                            "Pos": {
                                "X": 0,
                                "Y": 60
                            },
                            "Color": {
                                "R": 176,
                                "G": 160,
                                "B": 114
                            }
                        },
                        {
                            "Pos": {
                                "X": 12,
                                "Y": 60
                            },
                            "Color": {
                                "R": 176,
                                "G": 160,
                                "B": 114
                            }
                        },
                        {
                            "Pos": {
                                "X": 24,
                                "Y": 60
                            },
                            "Color": {
                                "R": 128,
                                "G": 116,
                                "B": 85
                            }
                        },
                        {
                            "Pos": {
                                "X": 36,
                                "Y": 60
                            },
                            "Color": {
                                "R": 176,
                                "G": 160,
                                "B": 114
                            }
                        },
                        {
                            "Pos": {
                                "X": 48,
                                "Y": 60
                            },
                            "Color": {
                                "R": 176,
                                "G": 160,
                                "B": 114
                            }
                        }
                    ]
                ],
                "isVisible": false,
                "used_colors": [
                    [
                        {
                            "R": 136,
                            "G": 124,
                            "B": 101
                        },
                        {
                            "R": 39,
                            "G": 79,
                            "B": 59
                        },
                        {
                            "R": 176,
                            "G": 163,
                            "B": 144
                        }
                    ]
                ]
            },
            {
                "blocks": [
                    [
                        {
                            "Pos": {
                                "X": 0,
                                "Y": 60
                            },
                            "Color": {
                                "R": 176,
                                "G": 160,
                                "B": 114
                            }
                        },
                        {
                            "Pos": {
                                "X": 12,
                                "Y": 60
                            },
                            "Color": {
                                "R": 176,
                                "G": 160,
                                "B": 114
                            }
                        },
                        {
                            "Pos": {
                                "X": 24,
                                "Y": 60
                            },
                            "Color": {
                                "R": 128,
                                "G": 116,
                                "B": 85
                            }
                        },
                        {
                            "Pos": {
                                "X": 36,
                                "Y": 60
                            },
                            "Color": {
                                "R": 176,
                                "G": 160,
                                "B": 114
                            }
                        },
                        {
                            "Pos": {
                                "X": 48,
                                "Y": 60
                            },
                            "Color": {
                                "R": 176,
                                "G": 160,
                                "B": 114
                            }
                        }
                    ]
                ],
                "isVisible": false,
                "used_colors": [
                    [
                        {
                            "R": 65,
                            "G": 40,
                            "B": 16
                        },
                        {
                            "R": 155,
                            "G": 138,
                            "B": 115
                        },
                        {
                            "R": 97,
                            "G": 104,
                            "B": 81
                        }
                    ]
                ]
            },
            {
                "blocks": [
                    [
                        {
                            "Pos": {
                                "X": 0,
                                "Y": 60
                            },
                            "Color": {
                                "R": 176,
                                "G": 160,
                                "B": 114
                            }
                        },
                        {
                            "Pos": {
                                "X": 12,
                                "Y": 60
                            },
                            "Color": {
                                "R": 176,
                                "G": 160,
                                "B": 114
                            }
                        },
                        {
                            "Pos": {
                                "X": 24,
                                "Y": 60
                            },
                            "Color": {
                                "R": 128,
                                "G": 116,
                                "B": 85
                            }
                        },
                        {
                            "Pos": {
                                "X": 36,
                                "Y": 60
                            },
                            "Color": {
                                "R": 176,
                                "G": 160,
                                "B": 114
                            }
                        },
                        {
                            "Pos": {
                                "X": 48,
                                "Y": 60
                            },
                            "Color": {
                                "R": 176,
                                "G": 160,
                                "B": 114
                            }
                        }
                    ]
                ],
                "isVisible": false,
                "used_colors": [
                    [
                        {
                            "R": 64,
                            "G": 87,
                            "B": 74
                        },
                        {
                            "R": 151,
                            "G": 131,
                            "B": 106
                        },
                        {
                            "R": 48,
                            "G": 27,
                            "B": 8
                        }
                    ]
                ]
            },
            {
                "blocks": [
                    [
                        {
                            "Pos": {
                                "X": 0,
                                "Y": 60
                            },
                            "Color": {
                                "R": 176,
                                "G": 160,
                                "B": 114
                            }
                        },
                        {
                            "Pos": {
                                "X": 12,
                                "Y": 60
                            },
                            "Color": {
                                "R": 176,
                                "G": 160,
                                "B": 114
                            }
                        },
                        {
                            "Pos": {
                                "X": 24,
                                "Y": 60
                            },
                            "Color": {
                                "R": 128,
                                "G": 116,
                                "B": 85
                            }
                        },
                        {
                            "Pos": {
                                "X": 36,
                                "Y": 60
                            },
                            "Color": {
                                "R": 176,
                                "G": 160,
                                "B": 114
                            }
                        },
                        {
                            "Pos": {
                                "X": 48,
                                "Y": 60
                            },
                            "Color": {
                                "R": 176,
                                "G": 160,
                                "B": 114
                            }
                        }
                    ]
                ],
                "isVisible": false,
                "used_colors": [
                    [
                        {
                            "R": 176,
                            "G": 160,
                            "B": 114
                        },
                        {
                            "R": 128,
                            "G": 116,
                            "B": 85
                        }
                    ]
                ]
            }
        ]
    ]
}